sphinxcontrib/eval/__init__.py
sphinxcontrib/eval/_version.py
sphinxcontrib/eval/myst.py
sphinxcontrib/eval/py.typed
sphinxcontrib/eval/rst.py
sphinxcontrib/eval/utils.py
sphinxcontrib_eval-0.0.3.dist-info/LICENSE
sphinxcontrib_eval-0.0.3.dist-info/METADATA
sphinxcontrib_eval-0.0.3.dist-info/WHEEL
sphinxcontrib_eval-0.0.3.dist-info/top_level.txt
sphinxcontrib_eval-0.0.3.dist-info/RECORD
