Metadata-Version: 2.1
Name: sphinxcontrib-eval
Version: 0.0.3
Summary: Evaluate shell command or python code in sphinx and myst
Author-email: Wu Zhenyu <wuzhenyu@ustc.edu>
License: GPL v3
Project-URL: Homepage, https://sphinxcontrib-eval.readthedocs.io
Project-URL: Download, https://github.com/Freed-Wu/sphinxcontrib-eval/releases
Project-URL: Bug Report, https://github.com/Freed-Wu/sphinxcontrib-eval/issues
Project-URL: Source, https://github.com/Freed-Wu/sphinxcontrib-eval
Keywords: sphinx,myst,eval
Classifier: Development Status :: 3 - Alpha
Classifier: Intended Audience :: Developers
Classifier: Topic :: Software Development :: Build Tools
Classifier: License :: OSI Approved :: GNU General Public License v3 (GPLv3)
Classifier: Operating System :: Microsoft :: Windows
Classifier: Operating System :: POSIX
Classifier: Operating System :: Unix
Classifier: Operating System :: MacOS
Classifier: Programming Language :: Python :: 3 :: Only
Classifier: Programming Language :: Python :: 3
Classifier: Programming Language :: Python :: 3.9
Classifier: Programming Language :: Python :: 3.10
Classifier: Programming Language :: Python :: 3.11
Requires-Python: >=3.9
License-File: LICENSE
Requires-Dist: sphinx
Provides-Extra: dev
Requires-Dist: myst-parser ; extra == 'dev'
Requires-Dist: pre-commit ; extra == 'dev'
Requires-Dist: pytest-cov ; extra == 'dev'
Requires-Dist: tomli ; extra == 'dev'
Provides-Extra: myst
Requires-Dist: myst-parser ; extra == 'myst'
